micropython_bmm150/__init__.py
micropython_bmm150/bmm150.py
micropython_bmm150/i2c_helpers.py
micropython_bmm150-0.1.0.dist-info/LICENSE
micropython_bmm150-0.1.0.dist-info/METADATA
micropython_bmm150-0.1.0.dist-info/WHEEL
micropython_bmm150-0.1.0.dist-info/top_level.txt
micropython_bmm150-0.1.0.dist-info/RECORD
