Metadata-Version: 2.1
Name: micropython-bmm150
Version: 0.1.0
Summary: MicroPython Driver for the Bosch BMM150 Magnetometer
Author-email: JDM <xxyx@mailmeto.mozmail.com>
License: MIT
Project-URL: Homepage, https://github.com/jposada202020/MicroPython_BMM150
Keywords: sensor,micropython,bmm150,micropython,driver,bosch,magnetometer,sensor,bmm150
Classifier: Intended Audience :: Developers
Classifier: Topic :: Software Development :: Libraries
Classifier: Topic :: Software Development :: Embedded Systems
Classifier: Topic :: System :: Hardware
Classifier: License :: OSI Approved :: MIT License
Classifier: Programming Language :: Python :: Implementation :: MicroPython
License-File: LICENSE
